simpy/io/__init__.py
simpy/io/access.py
simpy/io/async_module.py
simpy/io/base.py
simpy/io/broker.py
simpy/io/codec.py
simpy/io/dispatcher.py
simpy/io/http.py
simpy/io/json_module.py
simpy/io/message.py
simpy/io/network.py
simpy/io/packet.py
simpy/io/paths.py
simpy/io/platform.py
simpy/io/poll.py
simpy/io/select.py
simpy/io/virtual.py
simpy/io/websocket.py
SimPy.IO_SemVer-0.3.0rc20211014000428.dist-info/METADATA
SimPy.IO_SemVer-0.3.0rc20211014000428.dist-info/WHEEL
SimPy.IO_SemVer-0.3.0rc20211014000428.dist-info/top_level.txt
SimPy.IO_SemVer-0.3.0rc20211014000428.dist-info/RECORD
